myfletify/__init__.py
myfletify/converter.py
myfletify/parser.py
myfletify/utils.py
myfletify-0.1.0.dist-info/LICENSE
myfletify-0.1.0.dist-info/METADATA
myfletify-0.1.0.dist-info/WHEEL
myfletify-0.1.0.dist-info/RECORD
